gitanalytics/__init__.py
gitanalytics/ai_summarizer.py
gitanalytics/analytics.py
gitanalytics/cache_manager.py
gitanalytics/cli.py
gitanalytics/complexity_analyzer.py
gitanalytics/config.py
gitanalytics/cost_monitor.py
gitanalytics/git_analyzer.py
gitanalytics/historical_metrics.py
gitanalytics/language_detector.py
gitanalytics/model_selector.py
gitanalytics/report_builder.py
gitanalytics/security_analyzer.py
gitanalytics/utils.py
gitanalytics/templates/report.json.j2
gitanalytics/templates/report.md.j2
ai_gitanalytics_cli-0.5.0.dist-info/METADATA
ai_gitanalytics_cli-0.5.0.dist-info/WHEEL
ai_gitanalytics_cli-0.5.0.dist-info/entry_points.txt
ai_gitanalytics_cli-0.5.0.dist-info/RECORD
