Metadata-Version: 2.4
Name: ai-gitanalytics-cli
Version: 0.5.0
Summary: AI-powered Git repository analytics tool. Get insights on code churn, complexity, and security.
Project-URL: Homepage, https://github.com/bswnth48/gitanalytics
Project-URL: Bug Tracker, https://github.com/bswnth48/gitanalytics/issues
Author-email: bswnth48 <bswnth48@users.noreply.github.com>
License: MIT
Classifier: Development Status :: 4 - Beta
Classifier: Intended Audience :: Developers
Classifier: License :: OSI Approved :: MIT License
Classifier: Programming Language :: Python :: 3
Classifier: Programming Language :: Python :: 3.8
Classifier: Programming Language :: Python :: 3.9
Classifier: Programming Language :: Python :: 3.10
Classifier: Programming Language :: Python :: 3.11
Classifier: Topic :: Software Development :: Quality Assurance
Classifier: Topic :: Software Development :: Version Control :: Git
Requires-Python: >=3.8
Requires-Dist: bandit>=1.7.5
Requires-Dist: click>=8.0
Requires-Dist: gitpython>=3.1
Requires-Dist: jinja2>=3.0
Requires-Dist: openai>=1.12
Requires-Dist: psutil>=5.9.8
Requires-Dist: pydantic-settings>=2.0
Requires-Dist: pydantic>=2.0
Requires-Dist: radon>=6.0
Requires-Dist: requests>=2.31.0
Requires-Dist: rich>=13.0
Provides-Extra: dev
Requires-Dist: black>=24.0; extra == 'dev'
Requires-Dist: flake8>=7.0; extra == 'dev'
Requires-Dist: mypy>=1.0; extra == 'dev'
Requires-Dist: pytest>=7.0; extra == 'dev'
